fsquery/__init__.py
fsquery/fsquery.py
fsquery/utFSQuery.py
fsquery-0.3.0.dist-info/LICENSE.txt
fsquery-0.3.0.dist-info/METADATA
fsquery-0.3.0.dist-info/WHEEL
fsquery-0.3.0.dist-info/top_level.txt
fsquery-0.3.0.dist-info/RECORD
