Metadata-Version: 2.1
Name: fsquery
Version: 0.3.0
Summary: File System Query.       Working with the file system is too verbose. Let's make it more like JQuery.
Home-page: https://github.com/interstar/FSQuery
Author: Phil Jones
Author-email: interstar@gmail.com
License: MIT
Platform: UNKNOWN
Classifier: Development Status :: 3 - Alpha
Classifier: Intended Audience :: Developers
